salome/bin/salome/IDLparser.py
salome/bin/salome/KernelHelpersUseCases
salome/bin/salome/NSparam.py
salome/bin/salome/ORBConfigFile.py
salome/bin/salome/SALOMEDS_Client
salome/bin/salome/SALOMEDS_Server
salome/bin/salome/SALOME_ConnectionManagerServer
salome/bin/salome/SALOME_Container
salome/bin/salome/SALOME_ContainerPy.py
salome/bin/salome/SALOME_Container_No_NS_Serv
salome/bin/salome/SALOME_Container_No_NS_Serv_OutProcess
salome/bin/salome/SALOME_Container_No_NS_Serv_OutProcess_FT
salome/bin/salome/SALOME_Container_No_NS_Serv_OutProcess_Replay
salome/bin/salome/SALOME_Container_No_NS_Serv_OutProcess_Replay_FT
salome/bin/salome/SALOME_DataScopeServer
salome/bin/salome/SALOME_DataScopeServer_SSL
salome/bin/salome/SALOME_LauncherServer
salome/bin/salome/SALOME_Logger_Server
salome/bin/salome/SALOME_ModuleCatalog_Client
salome/bin/salome/SALOME_ModuleCatalog_Server
salome/bin/salome/SALOME_Registry_Server
salome/bin/salome/TestComponentPy.py
salome/bin/salome/TestContainer
salome/bin/salome/TestContainerManager
salome/bin/salome/TestLauncher
salome/bin/salome/TestLifeCycleCORBA.py
salome/bin/salome/TestLogger
salome/bin/salome/TestLogger.py
salome/bin/salome/TestModuleCatalog.py
salome/bin/salome/Test_LifeCycleCORBA
salome/bin/salome/VERSION
salome/bin/salome/addToKillList.py
salome/bin/salome/app-quickstart.py
salome/bin/salome/appli_clean.sh
salome/bin/salome/appli_gen.py
salome/bin/salome/dummyexe_loggerTraceCollector
salome/bin/salome/envSalome.py
salome/bin/salome/killSalome.py
salome/bin/salome/killSalomeWithPort.py
salome/bin/salome/prepare_generating_doc.py
salome/bin/salome/pythonpath_reduction.py
salome/bin/salome/runConsole.py
salome/bin/salome/runIDLparser
salome/bin/salome/runRemote.py
salome/bin/salome/runSalome.py
salome/bin/salome/runSalomeNoServer.py
salome/bin/salome/runSalomeOld.py
salome/bin/salome/runSalomeOnDemand.py
salome/bin/salome/salomeContext.py
salome/bin/salome/salome_process_attach
salome_kernel-9.14.0.post7.dist-info/METADATA
salome_kernel-9.14.0.post7.dist-info/WHEEL
salome_kernel-9.14.0.post7.dist-info/entry_points.txt
salome_kernel-9.14.0.post7.dist-info/RECORD
salome_kernel-9.14.0.post7.dist-info/sboms/auditwheel.cdx.json
