Metadata-Version: 1.2
Name: salome.kernel
Version: 9.14.0.post7
Summary: general services of SALOME platform
Home-page: https://github.com/SalomePlatform/kernel
Author: EDF R&D
Author-email: eric.fayolle@edf.fr
License: LGPL
Keywords: salome
Platform: any
Classifier: Development Status :: 5 - Production/Stable
Classifier: License :: OSI Approved :: GNU Lesser General Public License v3 or later (LGPLv3+)
Classifier: Programming Language :: C++
Classifier: Programming Language :: Python :: 3
Classifier: Topic :: Scientific/Engineering :: Physics
Classifier: Intended Audience :: Science/Research
Requires-Dist: numpy<2
Requires-Dist: psutil<6
Requires-Dist: salome-omniorb
Requires-Dist: packaging
